{
  "match_id": 266967,
  "match_date": "2015-03-14",
  "kick_off": "18:00:00.000",
  "competition": {
    "competition_id": 11,
    "country_name": "Spain",
    "competition_name": "La Liga"
  },
  "season": {
    "season_id": 26,
    "season_name": "2014/2015"
  },
  "home_team": {
    "home_team_id": 322,
    "home_team_name": "Eibar",
    "home_team_gender": "male",
    "home_team_group": null,
    "country": {
      "id": 214,
      "name": "Spain"
    },
    "managers": [
      {
        "id": 767,
        "name": "Gaizka Garitano Aguirre",
        "nickname": "Gaizka Garitano",
        "dob": "1975-07-09",
        "country": {
          "id": 214,
          "name": "Spain"
        }
      }
    ]
  },
  "away_team": {
    "away_team_id": 217,
    "away_team_name": "Barcelona",
    "away_team_gender": "male",
    "away_team_group": null,
    "country": {
      "id": 214,
      "name": "Spain"
    },
    "managers": [
      {
        "id": 793,
        "name": "Luis Enrique Mart\u00ednez Garc\u00eda",
        "nickname": "Luis Enrique",
        "dob": "1970-05-08",
        "country": {
          "id": 214,
          "name": "Spain"
        }
      }
    ]
  },
  "home_score": 0,
  "away_score": 2,
  "match_status": "available",
  "match_status_360": "scheduled",
  "last_updated": "2023-07-24T21:48:04.558640",
  "last_updated_360": "2021-06-13T16:17:31.694",
  "metadata": {
    "data_version": "1.1.0",
    "shot_fidelity_version": "2",
    "xy_fidelity_version": "2"
  },
  "match_week": 27,
  "competition_stage": {
    "id": 1,
    "name": "Regular Season"
  },
  "stadium": {
    "id": 347,
    "name": "Estadio Municipal de Ipur\u00faa",
    "country": {
      "id": 214,
      "name": "Spain"
    }
  }
}